task2/rom.sv
module rom #(
    parameter ADDRESS_WIDTH = 8,
              DATA_WIDTH = 8
)(
    input logic                     clk,
    input logic [ADDRESS_WIDTH-1:0] addr1,
    input logic [ADDRESS_WIDTH-1:0] addr2,
    output logic [DATA_WIDTH-1:0]   dout1,
    output logic [DATA_WIDTH-1:0]   dout2
);

logic [DATA_WIDTH-1:0] rom_array [2**ADDRESS_WIDTH-1:0];

initial begin
        $display("Loading rom.");
        $readmemh("sinerom.mem", rom_array);
end;

always_ff @(posedge clk) begin
    dout1 <= rom_array[addr1];
    dout2 <= rom_array[addr2];
    end 
endmodule

task2/counter.sv
module counter #(
    parameter INPUT_WIDTH = 8,
              OUTPUT_WIDTH = 8
)(
    input logic [INPUT_WIDTH-1:0] offset,
    input logic rst,
    input logic en,
    input logic clk,
    output logic [OUTPUT_WIDTH-1:0] count
);

always_ff @(posedge clk) begin
    if (rst) count <= '0;
    else if (en) count <= count + 1;
end

endmodule

task2/sinegen.sv
module sinegen #(
    parameter OFFSET_WIDTH = 8,
              A_WIDTH = 8,
              D_WIDTH = 8  
)(
    input logic [OFFSET_WIDTH-1:0] offset,
    input logic rst,
    input logic en,
    input logic clk,
    output logic [D_WIDTH-1:0] dout1,
    output logic [D_WIDTH-1:0] dout2
);

    logic [A_WIDTH-1:0] addr1, addr2;

counter addrCounter (
    .rst(rst),
    .en(en),
    .clk(clk),
    .count(addr1)
);

assign addr2 = addr1 + offset;

rom sinerom (
    .clk(clk),
    .addr1(addr1), 
    .addr2(addr2),
    .dout1(dout1),
    .dout2(dout2)   
);

endmodule

task2/sinegen.vcd
$version Generated by VerilatedVcd $end
$timescale 1ps $end
 $scope module TOP $end
  $var wire 8 # offset [7:0] $end
  $var wire 1 $ rst $end
  $var wire 1 % en $end
  $var wire 1 & clk $end
  $var wire 8 ' dout1 [7:0] $end
  $var wire 8 ( dout2 [7:0] $end
  $scope module sinegen $end
   $var wire 32 + OFFSET_WIDTH [31:0] $end
   $var wire 32 + A_WIDTH [31:0] $end
   $var wire 32 + D_WIDTH [31:0] $end
   $var wire 8 # offset [7:0] $end
   $var wire 1 $ rst $end
   $var wire 1 % en $end
   $var wire 1 & clk $end
   $var wire 8 ' dout1 [7:0] $end
   $var wire 8 ( dout2 [7:0] $end
   $var wire 8 ) addr1 [7:0] $end
   $var wire 8 * addr2 [7:0] $end
   $scope module addrCounter $end
    $var wire 32 + INPUT_WIDTH [31:0] $end
    $var wire 32 + OUTPUT_WIDTH [31:0] $end
    $var wire 8 , offset [7:0] $end
    $var wire 1 $ rst $end
    $var wire 1 % en $end
    $var wire 1 & clk $end
    $var wire 8 ) count [7:0] $end
   $upscope $end
   $scope module sinerom $end
    $var wire 32 + ADDRESS_WIDTH [31:0] $end
    $var wire 32 + DATA_WIDTH [31:0] $end
    $var wire 1 & clk $end
    $var wire 8 ) addr1 [7:0] $end
    $var wire 8 * addr2 [7:0] $end
    $var wire 8 ' dout1 [7:0] $end
    $var wire 8 ( dout2 [7:0] $end
   $upscope $end
  $upscope $end
 $upscope $end
$enddefinitions $end


#0
b00000000 #
0$
1%
1&
b00000000 '
b00000000 (
b00000000 )
b00000000 *
b00000000000000000000000000001000 +
b00000000 ,
#1
0&
#2
b00000101 #
1&
b11111110 '
b11111110 (
b00000001 )
b00000110 *
#3
0&
#4
1&
b11111101 '
b11111100 (
b00000010 )
b00000111 *
#5
0&
#6
1&
b00000011 )
b00001000 *
#7
0&
#8
1&
b11111011 (
b00000100 )
b00001001 *
#9
0&
#10
1&
b11111010 (
b00000101 )
b00001010 *
#11
0&
#12
1&
b00000110 )
b00001011 *
#13
0&
#14
1&
b11111100 '
b11111001 (
b00000111 )
b00001100 *
#15
0&
#16
1&
b11111000 (
b00001000 )
b00001101 *
#17
0&
#18
1&
b11111011 '
b11110111 (
b00001001 )
b00001110 *
#19
0&
#20
1&
b11111010 '
b11110110 (
b00001010 )
b00001111 *
#21
0&
#22
1&
b11110101 (
b00001011 )
b00010000 *
#23
0&
#24
1&
b11111001 '
b11110100 (
b00001100 )
b00010001 *
#25
0&
#26
1&
b11111000 '
b11110011 (
b00001101 )
b00010010 *
#27
0&
#28
1&
b11110111 '
b11110001 (
b00001110 )
b00010011 *
#29
0&
#30
1&
b11110110 '
b11110000 (
b00001111 )
b00010100 *
#31
0&
#32
1&
b11110101 '
b11101111 (
b00010000 )
b00010101 *
#33
0&
#34
1&
b11110100 '
b11101101 (
b00010001 )
b00010110 *
#35
0&
#36
1&
b11110011 '
b11101011 (
b00010010 )
b00010111 *
#37
0&
#38
1&
b11110001 '
b11101010 (
b00010011 )
b00011000 *
#39
0&
#40
1&
b11110000 '
b11101000 (
b00010100 )
b00011001 *
#41
0&
#42
1&
b11101111 '
b11100110 (
b00010101 )
b00011010 *
#43
0&
#44
1&
b11101101 '
b11100101 (
b00010110 )
b00011011 *
#45
0&
#46
1&
b11101011 '
b11100011 (
b00010111 )
b00011100 *
#47
0&
#48
1&
b11101010 '
b11100001 (
b00011000 )
b00011101 *
#49
0&
#50
1&
b11101000 '
b11011111 (
b00011001 )
b00011110 *
#51
0&
#52
1&
b11100110 '
b11011101 (
b00011010 )
b00011111 *
#53
0&
#54
1&
b11100101 '
b11011010 (
b00011011 )
b00100000 *
#55
0&
#56
1&
b11100011 '
b11011000 (
b00011100 )
b00100001 *
#57
0&
#58
1&
b11100001 '
b11010110 (
b00011101 )
b00100010 *
#59
0&
#60
1&
b11011111 '
b11010100 (
b00011110 )
b00100011 *
#61
0&
#62
1&
b11011101 '
b11010001 (
b00011111 )
b00100100 *
#63
0&
#64
1&
b11011010 '
b11001111 (
b00100000 )
b00100101 *
#65
0&
#66
1&
b11011000 '
b11001101 (
b00100001 )
b00100110 *
#67
0&
#68
1&
b11010110 '
b11001010 (
b00100010 )
b00100111 *
#69
0&
#70
1&
b11010100 '
b11001000 (
b00100011 )
b00101000 *
#71
0&
#72
1&
b11010001 '
b11000101 (
b00100100 )
b00101001 *
#73
0&
#74
1&
b11001111 '
b11000010 (
b00100101 )
b00101010 *
#75
0&
#76
1&
b11001101 '
b11000000 (
b00100110 )
b00101011 *
#77
0&
#78
1&
b11001010 '
b10111101 (
b00100111 )
b00101100 *
#79
0&
#80
1&
b11001000 '
b10111010 (
b00101000 )
b00101101 *
#81
0&
#82
1&
b11000101 '
b10111000 (
b00101001 )
b00101110 *
#83
0&
#84
1&
b11000010 '
b10110101 (
b00101010 )
b00101111 *
#85
0&
#86
1&
b11000000 '
b10110010 (
b00101011 )
b00110000 *
#87
0&
#88
1&
b10111101 '
b10101111 (
b00101100 )
b00110001 *
#89
0&
#90
1&
b10111010 '
b10101100 (
b00101101 )
b00110010 *
#91
0&
#92
1&
b10111000 '
b10101001 (
b00101110 )
b00110011 *
#93
0&
#94
1&
b10110101 '
b10100110 (
b00101111 )
b00110100 *
#95
0&
#96
1&
b10110010 '
b10100011 (
b00110000 )
b00110101 *
#97
0&
#98
1&
b10101111 '
b10100000 (
b00110001 )
b00110110 *
#99
0&
#100
1&
b10101100 '
b10011101 (
b00110010 )
b00110111 *
#101
0&
#102
1&
b10101001 '
b10011010 (
b00110011 )
b00111000 *
#103
0&
#104
1&
b10100110 '
b10010111 (
b00110100 )
b00111001 *
#105
0&
#106
1&
b10100011 '
b10010100 (
b00110101 )
b00111010 *
#107
0&
#108
1&
b10100000 '
b10010001 (
b00110110 )
b00111011 *
#109
0&
#110
1&
b10011101 '
b10001110 (
b00110111 )
b00111100 *
#111
0&
#112
1&
b10011010 '
b10001011 (
b00111000 )
b00111101 *
#113
0&
#114
1&
b10010111 '
b10001000 (
b00111001 )
b00111110 *
#115
0&
#116
1&
b10010100 '
b10000101 (
b00111010 )
b00111111 *
#117
0&
#118
1&
b10010001 '
b10000010 (
b00111011 )
b01000000 *
#119
0&
#120
1&
b10001110 '
b01111110 (
b00111100 )
b01000001 *
#121
0&
#122
1&
b10001011 '
b01111011 (
b00111101 )
b01000010 *
#123
0&
#124
1&
b10001000 '
b01111000 (
b00111110 )
b01000011 *
#125
0&
#126
1&
b10000101 '
b01110101 (
b00111111 )
b01000100 *
#127
0&
#128
1&
b10000010 '
b01110010 (
b01000000 )
b01000101 *
#129
0&
#130
1&
b01111110 '
b01101111 (
b01000001 )
b01000110 *
#131
0&
#132
1&
b01111011 '
b01101100 (
b01000010 )
b01000111 *
#133
0&
#134
1&
b01111000 '
b01101001 (
b01000011 )
b01001000 *
#135
0&
#136
1&
b01110101 '
b01100110 (
b01000100 )
b01001001 *
#137
0&
#138
1&
b01110010 '
b01100011 (
b01000101 )
b01001010 *
#139
0&
#140
1&
b01101111 '
b01100000 (
b01000110 )
b01001011 *
#141
0&
#142
1&
b01101100 '
b01011101 (
b01000111 )
b01001100 *
#143
0&
#144
1&
b01101001 '
b01011010 (
b01001000 )
b01001101 *
#145
0&
#146
1&
b01100110 '
b01010111 (
b01001001 )
b01001110 *
#147
0&
#148
1&
b01100011 '
b01010100 (
b01001010 )
b01001111 *
#149
0&
#150
1&
b01100000 '
b01010001 (
b01001011 )
b01010000 *
#151
0&
#152
1&
b01011101 '
b01001110 (
b01001100 )
b01010001 *
#153
0&
#154
1&
b01011010 '
b01001011 (
b01001101 )
b01010010 *
#155
0&
#156
1&
b01010111 '
b01001000 (
b01001110 )
b01010011 *
#157
0&
#158
1&
b01010100 '
b01000101 (
b01001111 )
b01010100 *
#159
0&
#160
1&
b01010001 '
b01000011 (
b01010000 )
b01010101 *
#161
0&
#162
1&
b01001110 '
b01000000 (
b01010001 )
b01010110 *
#163
0&
#164
1&
b01001011 '
b00111101 (
b01010010 )
b01010111 *
#165
0&
#166
1&
b01001000 '
b00111011 (
b01010011 )
b01011000 *
#167
0&
#168
1&
b01000101 '
b00111000 (
b01010100 )
b01011001 *
#169
0&
#170
1&
b01000011 '
b00110101 (
b01010101 )
b01011010 *
#171
0&
#172
1&
b01000000 '
b00110011 (
b01010110 )
b01011011 *
#173
0&
#174
1&
b00111101 '
b00110000 (
b01010111 )
b01011100 *
#175
0&
#176
1&
b00111011 '
b00101110 (
b01011000 )
b01011101 *
#177
0&
#178
1&
b00111000 '
b00101100 (
b01011001 )
b01011110 *
#179
0&
#180
1&
b00110101 '
b00101001 (
b01011010 )
b01011111 *
#181
0&
#182
1&
b00110011 '
b00100111 (
b01011011 )
b01100000 *
#183
0&
#184
1&
b00110000 '
b00100101 (
b01011100 )
b01100001 *
#185
0&
#186
1&
b00101110 '
b00100011 (
b01011101 )
b01100010 *
#187
0&
#188
1&
b00101100 '
b00100000 (
b01011110 )
b01100011 *
#189
0&
#190
1&
b00101001 '
b00011110 (
b01011111 )
b01100100 *
#191
0&
#192
1&
b00100111 '
b00011100 (
b01100000 )
b01100101 *
#193
0&
#194
1&
b00100101 '
b00011010 (
b01100001 )
b01100110 *
#195
0&
#196
1&
b00100011 '
b00011000 (
b01100010 )
b01100111 *
#197
0&
#198
1&
b00100000 '
b00010111 (
b01100011 )
b01101000 *
#199
0&
#200
1&
b00011110 '
b00010101 (
b01100100 )
b01101001 *
#201
0&
#202
1&
b00011100 '
b00010011 (
b01100101 )
b01101010 *
#203
0&
#204
1&
b00011010 '
b00010010 (
b01100110 )
b01101011 *
#205
0&
#206
1&
b00011000 '
b00010000 (
b01100111 )
b01101100 *
#207
0&
#208
1&
b00010111 '
b00001110 (
b01101000 )
b01101101 *
#209
0&
#210
1&
b00010101 '
b00001101 (
b01101001 )
b01101110 *
#211
0&
#212
1&
b00010011 '
b00001100 (
b01101010 )
b01101111 *
#213
0&
#214
1&
b00010010 '
b00001010 (
b01101011 )
b01110000 *
#215
0&
#216
1&
b00010000 '
b00001001 (
b01101100 )
b01110001 *
#217
0&
#218
1&
b00001110 '
b00001000 (
b01101101 )
b01110010 *
#219
0&
#220
1&
b00001101 '
b00000111 (
b01101110 )
b01110011 *
#221
0&
#222
1&
b00001100 '
b00000110 (
b01101111 )
b01110100 *
#223
0&
#224
1&
b00001010 '
b00000101 (
b01110000 )
b01110101 *
#225
0&
#226
1&
b00001001 '
b00000100 (
b01110001 )
b01110110 *
#227
0&
#228
1&
b00001000 '
b00000011 (
b01110010 )
b01110111 *
#229
0&
#230
1&
b00000111 '
b01110011 )
b01111000 *
#231
0&
#232
1&
b00000110 '
b00000010 (
b01110100 )
b01111001 *
#233
0&
#234
1&
b00000101 '
b00000001 (
b01110101 )
b01111010 *
#235
0&
#236
1&
b00000100 '
b01110110 )
b01111011 *
#237
0&
#238
1&
b00000011 '
b00000000 (
b01110111 )
b01111100 *
#239
0&
#240
1&
b01111000 )
b01111101 *
#241
0&
#242
1&
b00000010 '
b01111001 )
b01111110 *
#243
0&
#244
1&
b00000001 '
b01111010 )
b01111111 *
#245
0&
#246
1&
b01111011 )
b10000000 *
#247
0&
#248
1&
b00000000 '
b01111100 )
b10000001 *
#249
0&
#250
1&
b01111101 )
b10000010 *
#251
0&
#252
1&
b01111110 )
b10000011 *
#253
0&
#254
1&
b01111111 )
b10000100 *
#255
0&
#256
1&
b10000000 )
b10000101 *
#257
0&
#258
1&
b10000001 )
b10000110 *
#259
0&
#260
1&
b00000001 (
b10000010 )
b10000111 *
#261
0&
#262
1&
b10000011 )
b10001000 *
#263
0&
#264
1&
b00000010 (
b10000100 )
b10001001 *
#265
0&
#266
1&
b00000011 (
b10000101 )
b10001010 *
#267
0&
#268
1&
b10000110 )
b10001011 *
#269
0&
#270
1&
b00000001 '
b00000100 (
b10000111 )
b10001100 *
#271
0&
#272
1&
b00000101 (
b10001000 )
b10001101 *
#273
0&
#274
1&
b00000010 '
b00000110 (
b10001001 )
b10001110 *
#275
0&
#276
1&
b00000011 '
b00000111 (
b10001010 )
b10001111 *
#277
0&
#278
1&
b00001000 (
b10001011 )
b10010000 *
#279
0&
#280
1&
b00000100 '
b00001001 (
b10001100 )
b10010001 *
#281
0&
#282
1&
b00000101 '
b00001010 (
b10001101 )
b10010010 *
#283
0&
#284
1&
b00000110 '
b00001100 (
b10001110 )
b10010011 *
#285
0&
#286
1&
b00000111 '
b00001101 (
b10001111 )
b10010100 *
#287
0&
#288
1&
b00001000 '
b00001110 (
b10010000 )
b10010101 *
#289
0&
#290
1&
b00001001 '
b00010000 (
b10010001 )
b10010110 *
#291
0&
#292
1&
b00001010 '
b00010010 (
b10010010 )
b10010111 *
#293
0&
#294
1&
b00001100 '
b00010011 (
b10010011 )
b10011000 *
#295
0&
#296
1&
b00001101 '
b00010101 (
b10010100 )
b10011001 *
#297
0&
#298
1&
b00001110 '
b00010111 (
b10010101 )
b10011010 *
#299
0&
#300
1&
b00010000 '
b00011000 (
b10010110 )
b10011011 *
#301
0&
#302
1&
b00010010 '
b00011010 (
b10010111 )
b10011100 *
#303
0&
#304
1&
b00010011 '
b00011100 (
b10011000 )
b10011101 *
#305
0&
#306
1&
b00010101 '
b00011110 (
b10011001 )
b10011110 *
#307
0&
#308
1&
b00010111 '
b00100000 (
b10011010 )
b10011111 *
#309
0&
#310
1&
b00011000 '
b00100011 (
b10011011 )
b10100000 *
#311
0&
#312
1&
b00011010 '
b00100101 (
b10011100 )
b10100001 *
#313
0&
#314
1&
b00011100 '
b00100111 (
b10011101 )
b10100010 *
#315
0&
#316
1&
b00011110 '
b00101001 (
b10011110 )
b10100011 *
#317
0&
#318
1&
b00100000 '
b00101100 (
b10011111 )
b10100100 *
#319
0&
#320
1&
b00100011 '
b00101110 (
b10100000 )
b10100101 *
#321
0&
#322
1&
b00100101 '
b00110000 (
b10100001 )
b10100110 *
#323
0&
#324
1&
b00100111 '
b00110011 (
b10100010 )
b10100111 *
#325
0&
#326
b00000110 #
1&
b00101001 '
b00110101 (
b10100011 )
b10101001 *
#327
0&
#328
b00000111 #
1&
b00101100 '
b00111011 (
b10100100 )
b10101011 *
#329
0&
#330
b00001000 #
1&
b00101110 '
b01000000 (
b10100101 )
b10101101 *
#331
0&
#332
1&
b00110000 '
b01000101 (
b10100110 )
b10101110 *
#333
0&
#334
b00001001 #
1&
b00110011 '
b01001000 (
b10100111 )
b10110000 *
#335
0&
#336
1&
b00110101 '
b01001110 (
b10101000 )
b10110001 *
#337
0&
#338
1&
b00111000 '
b01010001 (
b10101001 )
b10110010 *
#339
0&
#340
b00001010 #
1&
b00111011 '
b01010100 (
b10101010 )
b10110100 *
#341
0&
#342
1&
b00111101 '
b01011010 (
b10101011 )
b10110101 *
#343
0&
#344
b00001100 #
1&
b01000000 '
b01011101 (
b10101100 )
b10111000 *
#345
0&
#346
b00001101 #
1&
b01000011 '
b01100110 (
b10101101 )
b10111010 *
#347
0&
#348
1&
b01000101 '
b01101100 (
b10101110 )
b10111011 *
#349
0&
#350
1&
b01001000 '
b01101111 (
b10101111 )
b10111100 *
#351
0&
#352
1&
b01001011 '
b01110010 (
b10110000 )
b10111101 *
#353
0&
#354
1&
b01001110 '
b01110101 (
b10110001 )
b10111110 *
#355
0&
#356
1&
b01010001 '
b01111000 (
b10110010 )
b10111111 *
#357
0&
#358
1&
b01010100 '
b01111011 (
b10110011 )
b11000000 *
#359
0&
#360
1&
b01010111 '
b01111111 (
b10110100 )
b11000001 *
#361
0&
#362
1&
b01011010 '
b10000010 (
b10110101 )
b11000010 *
#363
0&
#364
1&
b01011101 '
b10000101 (
b10110110 )
b11000011 *
#365
0&
#366
1&
b01100000 '
b10001000 (
b10110111 )
b11000100 *
#367
0&
#368
b00001110 #
1&
b01100011 '
b10001011 (
b10111000 )
b11000110 *
#369
0&
#370
b00001111 #
1&
b01100110 '
b10010001 (
b10111001 )
b11001000 *
#371
0&
#372
1&
b01101001 '
b10010111 (
b10111010 )
b11001001 *
#373
0&
#374
1&
b01101100 '
b10011010 (
b10111011 )
b11001010 *
#375
0&
#376
b00010000 #
1&
b01101111 '
b10011101 (
b10111100 )
b11001100 *
#377
0&
#378
1&
b01110010 '
b10100011 (
b10111101 )
b11001101 *
#379
0&
#380
1&
b01110101 '
b10100110 (
b10111110 )
b11001110 *
#381
0&
#382
1&
b01111000 '
b10101001 (
b10111111 )
b11001111 *
#383
0&
#384
1&
b01111011 '
b10101100 (
b11000000 )
b11010000 *
#385
0&
#386
b00010001 #
1&
b01111111 '
b10101111 (
b11000001 )
b11010010 *
#387
0&
#388
1&
b10000010 '
b10110101 (
b11000010 )
b11010011 *
#389
0&
#390
1&
b10000101 '
b10111000 (
b11000011 )
b11010100 *
#391
0&
#392
b00010010 #
1&
b10001000 '
b10111010 (
b11000100 )
b11010110 *
#393
0&
#394
1&
b10001011 '
b11000000 (
b11000101 )
b11010111 *
#395
0&
#396
1&
b10001110 '
b11000010 (
b11000110 )
b11011000 *
#397
0&
#398
1&
b10010001 '
b11000101 (
b11000111 )
b11011001 *
#399
0&
#400
b00010011 #
1&
b10010100 '
b11001000 (
b11001000 )
b11011011 *
#401
0&
#402
b00010110 #
1&
b10010111 '
b11001101 (
b11001001 )
b11011111 *
#403
0&
#404
b00011001 #
1&
b10011010 '
b11010110 (
b11001010 )
b11100011 *
#405
0&
#406
1&
b10011101 '
b11011111 (
b11001011 )
b11100100 *
#407
0&
#408
b00011010 #
1&
b10100000 '
b11100001 (
b11001100 )
b11100110 *
#409
0&
#410
1&
b10100011 '
b11100101 (
b11001101 )
b11100111 *
#411
0&
#412
b00011011 #
1&
b10100110 '
b11100110 (
b11001110 )
b11101001 *
#413
0&
#414
1&
b10101001 '
b11101010 (
b11001111 )
b11101010 *
#415
0&
#416
b00011100 #
1&
b10101100 '
b11101011 (
b11010000 )
b11101100 *
#417
0&
#418
b00011101 #
1&
b10101111 '
b11101111 (
b11010001 )
b11101110 *
#419
0&
#420
1&
b10110010 '
b11110001 (
b11010010 )
b11101111 *
#421
0&
#422
b00011110 #
1&
b10110101 '
b11110011 (
b11010011 )
b11110001 *
#423
0&
#424
1&
b10111000 '
b11110101 (
b11010100 )
b11110010 *
#425
0&
#426
b00011111 #
1&
b10111010 '
b11110110 (
b11010101 )
b11110100 *
#427
0&
#428
1&
b10111101 '
b11111000 (
b11010110 )
b11110101 *
#429
0&
#430
1&
b11000000 '
b11111001 (
b11010111 )
b11110110 *
#431
0&
#432
b00100000 #
1&
b11000010 '
b11111010 (
b11011000 )
b11111000 *
#433
0&
#434
1&
b11000101 '
b11111011 (
b11011001 )
b11111001 *
#435
0&
#436
b00100001 #
1&
b11001000 '
b11111100 (
b11011010 )
b11111011 *
#437
0&
#438
1&
b11001010 '
b11111101 (
b11011011 )
b11111100 *
#439
0&
#440
b00100010 #
1&
b11001101 '
b11011100 )
b11111110 *
#441
0&
#442
b00100011 #
1&
b11001111 '
b11011101 )
b00000000 *
#443
0&
#444
b00100100 #
1&
b11010001 '
b11111110 (
b11011110 )
b00000010 *
#445
0&
#446
b00100101 #
1&
b11010100 '
b11111101 (
b11011111 )
b00000100 *
#447
0&
#448
1&
b11010110 '
b11100000 )
b00000101 *
#449
0&
#450
b00100110 #
1&
b11011000 '
b11100001 )
b00000111 *
#451
0&
#452
1&
b11011010 '
b11111100 (
b11100010 )
b00001000 *
#453
0&
#454
1&
b11011101 '
b11111011 (
b11100011 )
b00001001 *
#455
0&
#456
b00100111 #
1&
b11011111 '
b11111010 (
b11100100 )
b00001011 *
#457
0&
#458
b00101000 #
1&
b11100001 '
b11111001 (
b11100101 )
b00001101 *
#459
0&
#460
1&
b11100011 '
b11110111 (
b11100110 )
b00001110 *
#461
0&
#462
b00101001 #
1&
b11100101 '
b11110110 (
b11100111 )
b00010000 *
#463
0&
#464
1&
b11100110 '
b11110100 (
b11101000 )
b00010001 *
#465
0&
#466
1&
b11101000 '
b11110011 (
b11101001 )
b00010010 *
#467
0&
#468
b00101011 #
1&
b11101010 '
b11110001 (
b11101010 )
b00010101 *
#469
0&
#470
b00101100 #
1&
b11101011 '
b11101101 (
b11101011 )
b00010111 *
#471
0&
#472
1&
b11101101 '
b11101010 (
b11101100 )
b00011000 *
#473
0&
#474
1&
b11101111 '
b11101000 (
b11101101 )
b00011001 *
#475
0&
#476
1&
b11110000 '
b11100110 (
b11101110 )
b00011010 *
#477
0&
#478
1&
b11110001 '
b11100101 (
b11101111 )
b00011011 *
#479
0&
#480
1&
b11110011 '
b11100011 (
b11110000 )
b00011100 *
#481
0&
#482
1&
b11110100 '
b11100001 (
b11110001 )
b00011101 *
#483
0&
#484
1&
b11110101 '
b11011111 (
b11110010 )
b00011110 *
#485
0&
#486
1&
b11110110 '
b11011101 (
b11110011 )
b00011111 *
#487
0&
#488
1&
b11110111 '
b11011010 (
b11110100 )
b00100000 *
#489
0&
#490
1&
b11111000 '
b11011000 (
b11110101 )
b00100001 *
#491
0&
#492
1&
b11111001 '
b11010110 (
b11110110 )
b00100010 *
#493
0&
#494
1&
b11111010 '
b11010100 (
b11110111 )
b00100011 *
#495
0&
#496
1&
b11010001 (
b11111000 )
b00100100 *
#497
0&
#498
1&
b11111011 '
b11001111 (
b11111001 )
b00100101 *
#499
0&
#500
1&
b11111100 '
b11001101 (
b11111010 )
b00100110 *
#501
0&
#502
1&
b11001010 (
b11111011 )
b00100111 *
#503
0&
#504
1&
b11111101 '
b11001000 (
b11111100 )
b00101000 *
#505
0&
#506
1&
b11000101 (
b11111101 )
b00101001 *
#507
0&
#508
1&
b11000010 (
b11111110 )
b00101010 *
#509
0&
#510
1&
b11000000 (
b11111111 )
b00101011 *
#511
0&
#512
1&
b10111101 (
b00000000 )
b00101100 *
#513
0&
#514
1&
b11111110 '
b10111010 (
b00000001 )
b00101101 *
#515
0&
#516
1&
b11111101 '
b10111000 (
b00000010 )
b00101110 *
#517
0&
#518
1&
b10110101 (
b00000011 )
b00101111 *
#519
0&
#520
1&
b10110010 (
b00000100 )
b00110000 *
#521
0&
#522
b00101101 #
1&
b10101111 (
b00000101 )
b00110010 *
#523
0&
#524
1&
b10101001 (
b00000110 )
b00110011 *
#525
0&
#526
b00101110 #
1&
b11111100 '
b10100110 (
b00000111 )
b00110101 *
#527
0&
#528
1&
b10100000 (
b00001000 )
b00110110 *
#529
0&
#530
b00101111 #
1&
b11111011 '
b10011101 (
b00001001 )
b00111000 *
#531
0&
#532
b00110000 #
1&
b11111010 '
b10010111 (
b00001010 )
b00111010 *
#533
0&
#534
1&
b10010001 (
b00001011 )
b00111011 *
#535
0&
#536
b00110001 #
1&
b11111001 '
b10001110 (
b00001100 )
b00111101 *
#537
0&
#538
b00110010 #
1&
b11111000 '
b10001000 (
b00001101 )
b00111111 *
#539
0&
#540
b00110100 #
1&
b11110111 '
b10000010 (
b00001110 )
b01000010 *
#541
0&
#542
b00110101 #
1&
b11110110 '
b01111000 (
b00001111 )
b01000100 *
#543
0&
#544
b00110110 #
1&
b11110101 '
b01110010 (
b00010000 )
b01000110 *
#545
0&
#546
b00110111 #
1&
b11110100 '
b01101100 (
b00010001 )
b01001000 *
#547
0&
#548
b00111000 #
1&
b11110011 '
b01100110 (
b00010010 )
b01001010 *
#549
0&
#550
b00111001 #
1&
b11110001 '
b01100000 (
b00010011 )
b01001100 *
#551
0&
#552
1&
b11110000 '
b01011010 (
b00010100 )
b01001101 *
#553
0&
#554
1&
b11101111 '
b01010111 (
b00010101 )
b01001110 *
#555
0&
#556
1&
b11101101 '
b01010100 (
b00010110 )
b01001111 *
#557
0&
#558
1&
b11101011 '
b01010001 (
b00010111 )
b01010000 *
#559
0&
#560
1&
b11101010 '
b01001110 (
b00011000 )
b01010001 *
#561
0&
#562
1&
b11101000 '
b01001011 (
b00011001 )
b01010010 *
#563
0&
#564
1&
b11100110 '
b01001000 (
b00011010 )
b01010011 *
#565
0&
#566
1&
b11100101 '
b01000101 (
b00011011 )
b01010100 *
#567
0&
#568
1&
b11100011 '
b01000011 (
b00011100 )
b01010101 *
#569
0&
#570
1&
b11100001 '
b01000000 (
b00011101 )
b01010110 *
#571
0&
#572
1&
b11011111 '
b00111101 (
b00011110 )
b01010111 *
#573
0&
#574
1&
b11011101 '
b00111011 (
b00011111 )
b01011000 *
#575
0&
#576
1&
b11011010 '
b00111000 (
b00100000 )
b01011001 *
#577
0&
#578
1&
b11011000 '
b00110101 (
b00100001 )
b01011010 *
#579
0&
#580
1&
b11010110 '
b00110011 (
b00100010 )
b01011011 *
#581
0&
#582
1&
b11010100 '
b00110000 (
b00100011 )
b01011100 *
#583
0&
#584
1&
b11010001 '
b00101110 (
b00100100 )
b01011101 *
#585
0&
#586
1&
b11001111 '
b00101100 (
b00100101 )
b01011110 *
#587
0&
#588
b00111010 #
1&
b11001101 '
b00101001 (
b00100110 )
b01100000 *
#589
0&
#590
1&
b11001010 '
b00100101 (
b00100111 )
b01100001 *
#591
0&
#592
1&
b11001000 '
b00100011 (
b00101000 )
b01100010 *
#593
0&
#594
1&
b11000101 '
b00100000 (
b00101001 )
b01100011 *
#595
0&
#596
1&
b11000010 '
b00011110 (
b00101010 )
b01100100 *
#597
0&
#598
b00111011 #
1&
b11000000 '
b00011100 (
b00101011 )
b01100110 *
#599
0&
#600
1&
b10111101 '
b00011000 (
b00101100 )
b01100111 *
#601
0&
#602
1&
b10111010 '
b00010111 (
b00101101 )
b01101000 *
#603
0&
#604
1&
b10111000 '
b00010101 (
b00101110 )
b01101001 *
#605
0&
#606
b00111100 #
1&
b10110101 '
b00010011 (
b00101111 )
b01101011 *
#607
0&
#608
1&
b10110010 '
b00010000 (
b00110000 )
b01101100 *
#609
0&
#610
1&
b10101111 '
b00001110 (
b00110001 )
b01101101 *
#611
0&
#612
1&
b10101100 '
b00001101 (
b00110010 )
b01101110 *
#613
0&
#614
b00111101 #
1&
b10101001 '
b00001100 (
b00110011 )
b01110000 *
#615
0&
#616
1&
b10100110 '
b00001001 (
b00110100 )
b01110001 *
#617
0&
#618
1&
b10100011 '
b00001000 (
b00110101 )
b01110010 *
#619
0&
#620
b00111110 #
1&
b10100000 '
b00000111 (
b00110110 )
b01110100 *
#621
0&
#622
1&
b10011101 '
b00000101 (
b00110111 )
b01110101 *
#623
0&
#624
1&
b10011010 '
b00000100 (
b00111000 )
b01110110 *
#625
0&
#626
b00111111 #
1&
b10010111 '
b00000011 (
b00111001 )
b01111000 *
#627
0&
#628
1&
b10010100 '
b00000010 (
b00111010 )
b01111001 *
#629
0&
#630
1&
b10010001 '
b00000001 (
b00111011 )
b01111010 *
#631
0&
#632
1&
b10001110 '
b00111100 )
b01111011 *
#633
0&
#634
1&
b10001011 '
b00000000 (
b00111101 )
b01111100 *
#635
0&
#636
1&
b10001000 '
b00111110 )
b01111101 *
#637
0&
#638
1&
b10000101 '
b00111111 )
b01111110 *
#639
0&
#640
1&
b10000010 '
b01000000 )
b01111111 *
#641
0&
#642
1&
b01111110 '
b01000001 )
b10000000 *
#643
0&
#644
b01000000 #
1&
b01111011 '
b01000010 )
b10000010 *
#645
0&
#646
1&
b01111000 '
b01000011 )
b10000011 *
#647
0&
#648
1&
b01110101 '
b01000100 )
b10000100 *
#649
0&
#650
1&
b01110010 '
b01000101 )
b10000101 *
#651
0&
#652
1&
b01101111 '
b01000110 )
b10000110 *
#653
0&
#654
1&
b01101100 '
b00000001 (
b01000111 )
b10000111 *
#655
0&
#656
1&
b01101001 '
b01001000 )
b10001000 *
#657
0&
#658
1&
b01100110 '
b00000010 (
b01001001 )
b10001001 *
#659
0&
#660
1&
b01100011 '
b00000011 (
b01001010 )
b10001010 *
#661
0&
#662
1&
b01100000 '
b01001011 )
b10001011 *
#663
0&
#664
1&
b01011101 '
b00000100 (
b01001100 )
b10001100 *
#665
0&
#666
1&
b01011010 '
b00000101 (
b01001101 )
b10001101 *
#667
0&
#668
1&
b01010111 '
b00000110 (
b01001110 )
b10001110 *
#669
0&
#670
1&
b01010100 '
b00000111 (
b01001111 )
b10001111 *
#671
0&
#672
1&
b01010001 '
b00001000 (
b01010000 )
b10010000 *
#673
0&
